comfyui_workflow_client-0.1.0.dist-info/licenses/LICENSE
comfyuiclient/__init__.py
comfyuiclient/client.py
comfyui_workflow_client-0.1.0.dist-info/METADATA
comfyui_workflow_client-0.1.0.dist-info/WHEEL
comfyui_workflow_client-0.1.0.dist-info/top_level.txt
comfyui_workflow_client-0.1.0.dist-info/RECORD
