Metadata-Version: 2.4
Name: comfyui-workflow-client
Version: 0.1.0
Summary: A Python client for ComfyUI API
Home-page: https://github.com/sugarkwork/Comfyui_api_client
Author: sugarkwork
Project-URL: Bug Reports, https://github.com/sugarkwork/Comfyui_api_client/issues
Project-URL: Source, https://github.com/sugarkwork/Comfyui_api_client
Keywords: comfyui api client stable-diffusion
Classifier: Development Status :: 3 - Alpha
Classifier: Intended Audience :: Developers
Classifier: Topic :: Software Development :: Libraries :: Python Modules
Classifier: License :: OSI Approved :: MIT License
Classifier: Programming Language :: Python :: 3
Classifier: Programming Language :: Python :: 3.7
Classifier: Programming Language :: Python :: 3.8
Classifier: Programming Language :: Python :: 3.9
Classifier: Programming Language :: Python :: 3.10
Classifier: Programming Language :: Python :: 3.11
Requires-Python: >=3.7
License-File: LICENSE
Requires-Dist: requests
Requires-Dist: aiohttp
Requires-Dist: pillow
Dynamic: author
Dynamic: classifier
Dynamic: description
Dynamic: description-content-type
Dynamic: home-page
Dynamic: keywords
Dynamic: license-file
Dynamic: project-url
Dynamic: requires-dist
Dynamic: requires-python
Dynamic: summary
